crop_energy_balance/crop.py
crop_energy_balance/inputs.py
crop_energy_balance/params.py
crop_energy_balance/solver.py
crop_energy_balance/utils.py
crop_energy_balance/version.py
crop_energy_balance/formalisms/canopy.py
crop_energy_balance/formalisms/component.py
crop_energy_balance/formalisms/config.py
crop_energy_balance/formalisms/irradiance.py
crop_energy_balance/formalisms/leaf.py
crop_energy_balance/formalisms/lumped_leaves.py
crop_energy_balance/formalisms/soil.py
crop_energy_balance/formalisms/sunlit_shaded_leaves.py
crop_energy_balance/formalisms/weather.py
crop_energy_balance-1.3.0.dist-info/licenses/LICENSE
crop_energy_balance-1.3.0.dist-info/METADATA
crop_energy_balance-1.3.0.dist-info/WHEEL
crop_energy_balance-1.3.0.dist-info/top_level.txt
crop_energy_balance-1.3.0.dist-info/RECORD
